{
	"instance" : {
		"shopCredentials" : "RichardPillar 7/5/2018 22:12",
		"renderGetTransactionsNowButtonsOn:" : "RichardPillar 9/2/2018 22:13",
		"checkShopActiveStatus:" : "RichardPillar 2/21/2018 08:31",
		"scriptAddTransactionDataLine:" : "RichardPillar 9/2/2018 22:11",
		"checkShopCredentials:" : "RichardPillar 2/16/2018 08:17",
		"renderGetTransactionsButtonsOn:" : "RichardPillar 1/18/2018 08:04",
		"renderGetTransactionsEndDateOn:" : "RichardPillar 2/1/2018 08:05",
		"getTransactions" : "RichardPillar 2/26/2018 18:19",
		"getShopNames" : "RichardPillar 1/11/2018 08:13",
		"startTime" : "RichardPillar 1/15/2018 16:57",
		"scriptAddTransactionDataLine:with:" : "RichardPillar 3/1/2018 21:32",
		"renderGetTransactionsStartTimeOn:" : "RichardPillar 1/31/2018 20:12",
		"parseGetEBayTransactionsResponse:" : "RichardPillar 2/13/2018 22:54",
		"parseShopName:" : "RichardPillar 2/8/2018 08:29",
		"renderGetTransactionsShopSelectOn:" : "RichardPillar 1/11/2018 08:13",
		"initialize" : "RichardPillar 1/18/2018 08:18",
		"messageComponent:" : "RichardPillar 1/10/2018 23:00",
		"startTime:" : "RichardPillar 1/15/2018 16:57",
		"scheduleFlag" : "RichardPillar 1/15/2018 07:58",
		"endDate" : "RichardPillar 2/1/2018 08:03",
		"startDate:" : "RichardPillar 1/11/2018 08:23",
		"validateGetTransactions" : "RichardPillar 2/21/2018 08:31",
		"messageComponent" : "RichardPillar 1/10/2018 23:00",
		"renderGetTransactionsScheduleButtonsOn:" : "RichardPillar 1/16/2018 08:40",
		"getShopStatus:" : "RichardPillar 2/21/2018 08:16",
		"renderGetTransactionsContentOn:" : "RichardPillar 9/2/2018 22:14",
		"shopName" : "RichardPillar 1/10/2018 23:00",
		"renderGetTransactionsDataTableOn:" : "RichardPillar 2/28/2018 08:11",
		"getShopCredentials:" : "RichardPillar 2/8/2018 08:30",
		"renderTransactionDataLineOn:with:" : "RichardPillar 2/28/2018 07:48",
		"shopName:" : "RichardPillar 1/10/2018 23:00",
		"tableRowCounter:" : "RichardPillar 7/5/2018 22:08",
		"renderGetTransactionsDatesOn:" : "RichardPillar 1/18/2018 08:00",
		"shopCredentials:" : "RichardPillar 7/5/2018 22:12",
		"channelNames:" : "RichardPillar 1/11/2018 08:16",
		"scheduleFlag:" : "RichardPillar 1/15/2018 07:58",
		"endDate:" : "RichardPillar 2/1/2018 08:03",
		"channelNames" : "RichardPillar 1/11/2018 08:16",
		"scriptResetForm:" : "RichardPillar 9/2/2018 22:21",
		"renderGetTransactionsFormOn:" : "RichardPillar 1/19/2018 08:09",
		"renderGetTransactionsActionCloseOn:" : "RichardPillar 1/10/2018 22:59",
		"renderGetTransactionsStartDateOn:" : "RichardPillar 1/31/2018 20:10",
		"tableRowCounter" : "RichardPillar 7/5/2018 22:08",
		"channel" : "RichardPillar 1/10/2018 23:00",
		"renderGetTransactionsScheduleDateOn:" : "RichardPillar 1/31/2018 20:11",
		"renderContentOn:" : "RichardPillar 9/2/2018 22:09",
		"startDate" : "RichardPillar 1/11/2018 08:23",
		"channel:" : "RichardPillar 1/10/2018 23:00",
		"getTransactionDataFor:" : "RichardPillar 3/3/2018 20:18"
	},
	"class" : { }
}